MANIFEST.in
README.md
setup.cfg
setup.py
src/avalonBG/__init__.py
src/avalonBG/db_utils.py
src/avalonBG/exception.py
src/avalonBG/games.py
src/avalonBG/mp3.py
src/avalonBG/quests.py
src/avalonBG/rules.py
src/avalonBG.egg-info/PKG-INFO
src/avalonBG.egg-info/SOURCES.txt
src/avalonBG.egg-info/dependency_links.txt
src/avalonBG.egg-info/requires.txt
src/avalonBG.egg-info/top_level.txt
src/avalonBG/resources/__init__.py
src/avalonBG/resources/rules.json
src/avalonBG/resources/audio/__init__.py
src/avalonBG/resources/audio/add_per_mor.mp3
src/avalonBG/resources/audio/end.mp3
src/avalonBG/resources/audio/init.mp3
src/avalonBG/resources/audio/merlin_identi.mp3
src/avalonBG/resources/audio/mordred.mp3
src/avalonBG/resources/audio/oberon.mp3
src/avalonBG/resources/audio/red_identi.mp3
src/avalonBG/resources/audio/serv_mord.mp3
test/test_mp3.py
test/test_requests.py
test/test_rules.py