Metadata-Version: 1.0
Name: avalonBG
Version: 1.0.1
Summary: avalon: avalon board game package
Home-page: UNKNOWN
Author: Romain Thierry-Laumont
Author-email: UNKNOWN
License: UNKNOWN
Platform: UNKNOWN
